ewoksjob/__init__.py
ewoksjob/__main__.py
ewoksjob/_patch.py
ewoksjob/bindings.py
ewoksjob/config.py
ewoksjob/apps/__init__.py
ewoksjob/apps/arguments.py
ewoksjob/apps/errors.py
ewoksjob/apps/ewoks.py
ewoksjob/cli_utils/__init__.py
ewoksjob/cli_utils/cancel.py
ewoksjob/cli_utils/submit.py
ewoksjob/client/__init__.py
ewoksjob/client/async_state.py
ewoksjob/client/dummy_workflow.py
ewoksjob/client/futures.py
ewoksjob/client/celery/__init__.py
ewoksjob/client/celery/futures.py
ewoksjob/client/celery/tasks.py
ewoksjob/client/celery/utils.py
ewoksjob/client/local/__init__.py
ewoksjob/client/local/futures.py
ewoksjob/client/local/pool.py
ewoksjob/client/local/tasks.py
ewoksjob/client/local/utils.py
ewoksjob/events/__init__.py
ewoksjob/events/handlers/__init__.py
ewoksjob/events/handlers/redis.py
ewoksjob/events/readers/__init__.py
ewoksjob/events/readers/base.py
ewoksjob/events/readers/redis.py
ewoksjob/events/readers/sqlite3.py
ewoksjob/tests/__init__.py
ewoksjob/tests/conftest.py
ewoksjob/tests/test_cancel.py
ewoksjob/tests/test_cli.py
ewoksjob/tests/test_config.py
ewoksjob/tests/test_convert.py
ewoksjob/tests/test_convert_and_execute.py
ewoksjob/tests/test_events.py
ewoksjob/tests/test_execute.py
ewoksjob/tests/test_execute_and_upload.py
ewoksjob/tests/test_feedback.py
ewoksjob/tests/test_future.py
ewoksjob/tests/test_futures.py
ewoksjob/tests/test_task_discovery.py
ewoksjob/tests/utils.py
ewoksjob/worker/__init__.py
ewoksjob/worker/executor.py
ewoksjob/worker/options.py
ewoksjob/worker/process.py
ewoksjob/worker/process_utils.py
ewoksjob/worker/slurm.py
ewoksjob-1.4.0.dist-info/licenses/LICENSE.md
ewoksjob-1.4.0.dist-info/METADATA
ewoksjob-1.4.0.dist-info/WHEEL
ewoksjob-1.4.0.dist-info/entry_points.txt
ewoksjob-1.4.0.dist-info/top_level.txt
ewoksjob-1.4.0.dist-info/RECORD
