Metadata-Version: 2.4
Name: ewoksjob
Version: 1.4.0
Summary: Asynchronous and distributed scheduling of Ewoks workflows from python
Author-email: ESRF <dau-pydev@esrf.fr>
License: # MIT License
Project-URL: Homepage, https://gitlab.esrf.fr/workflow/ewoks/ewoksjob/
Project-URL: Documentation, https://ewoksjob.readthedocs.io/
Project-URL: Repository, https://gitlab.esrf.fr/workflow/ewoks/ewoksjob/
Project-URL: Issues, https://gitlab.esrf.fr/workflow/ewoks/ewoksjob/issues
Project-URL: Changelog, https://gitlab.esrf.fr/workflow/ewoks/ewoksjob/-/blob/main/CHANGELOG.md
Classifier: Intended Audience :: Science/Research
Classifier: License :: OSI Approved :: MIT License
Classifier: Programming Language :: Python :: 3
Requires-Python: >=3.8
License-File: LICENSE.md
Requires-Dist: celery[tblib]>=5.5
Requires-Dist: ewoksutils[full]>=1.9.1
Requires-Dist: pyyaml
Provides-Extra: worker
Requires-Dist: ewoks>=4.0.0; extra == "worker"
Provides-Extra: redis
Requires-Dist: redis!=5.3.0b1,!=5.3.0b3; extra == "redis"
Provides-Extra: sql
Requires-Dist: sqlalchemy; extra == "sql"
Provides-Extra: monitor
Requires-Dist: flower; extra == "monitor"
Provides-Extra: slurm
Requires-Dist: pyslurmutils>=1.0; extra == "slurm"
Requires-Dist: gevent; extra == "slurm"
Provides-Extra: beacon
Requires-Dist: blissdata; extra == "beacon"
Provides-Extra: blissclient
Requires-Dist: ewoksjob[redis]; extra == "blissclient"
Requires-Dist: ewoksjob[beacon]; extra == "blissclient"
Provides-Extra: blissworker
Requires-Dist: ewoksjob[worker]; extra == "blissworker"
Requires-Dist: ewoksjob[redis]; extra == "blissworker"
Requires-Dist: ewoksjob[beacon]; extra == "blissworker"
Requires-Dist: ewoksjob[slurm]; extra == "blissworker"
Requires-Dist: ewoksjob[monitor]; extra == "blissworker"
Requires-Dist: ewoks[esrf-data-portal]; extra == "blissworker"
Requires-Dist: blissdata[tango]; extra == "blissworker"
Provides-Extra: test
Requires-Dist: ewoksjob[blissworker]; extra == "test"
Requires-Dist: ewoksjob[sql]; extra == "test"
Requires-Dist: pytest>=7; extra == "test"
Requires-Dist: pytest-celery; extra == "test"
Requires-Dist: pytest-redis; extra == "test"
Requires-Dist: mirakuru<3; python_version < "3.10" and extra == "test"
Requires-Dist: pytest-mock; extra == "test"
Requires-Dist: tzdata; extra == "test"
Requires-Dist: pytest-timeout; extra == "test"
Provides-Extra: dev
Requires-Dist: ewoksjob[test]; extra == "dev"
Requires-Dist: black>=25; extra == "dev"
Requires-Dist: flake8>=4; extra == "dev"
Requires-Dist: isort; extra == "dev"
Provides-Extra: doc
Requires-Dist: ewoksjob[worker]; extra == "doc"
Requires-Dist: ewoksjob[redis]; extra == "doc"
Requires-Dist: sphinx>=4.5; extra == "doc"
Requires-Dist: sphinx-autodoc-typehints>=1.16; extra == "doc"
Requires-Dist: pydata_sphinx_theme<0.15; extra == "doc"
Requires-Dist: sphinx-copybutton; extra == "doc"
Dynamic: license-file
